LICENSE
MANIFEST.in
README.rst
setup.cfg
setup.py
pretix_twilio/__init__.py
pretix_twilio/forms.py
pretix_twilio/signals.py
pretix_twilio/tasks.py
pretix_twilio/urls.py
pretix_twilio/views.py
pretix_twilio.egg-info/PKG-INFO
pretix_twilio.egg-info/SOURCES.txt
pretix_twilio.egg-info/dependency_links.txt
pretix_twilio.egg-info/entry_points.txt
pretix_twilio.egg-info/requires.txt
pretix_twilio.egg-info/top_level.txt
pretix_twilio/locale/de/LC_MESSAGES/django.po
pretix_twilio/locale/de_Informal/.gitkeep
pretix_twilio/locale/de_Informal/LC_MESSAGES/django.po
pretix_twilio/static/pretix_twilio/.gitkeep
pretix_twilio/templates/pretix_twilio/.gitkeep
pretix_twilio/templates/pretix_twilio/settings.html
pretix_twilio/templates/pretix_twilio/settings_template_fragment.html