Metadata-Version: 1.0
Name: pretix-twilio
Version: 0.9.0
Summary: Additionally to sending emails with pretix, send SMS to your customers with Twilio! Uses the built-in phone number field.
Home-page: https://github.com/rixx/pretix-twilio
Author: Tobias Kunze
Author-email: r@rixx.de
License: Apache
Platform: UNKNOWN
